{
  "mainimagePath":"assets/images/me.png",
  "mainmessage": "About Me",

  "containerData":[
    {
      "id": 0,
      "imagePath": "assets/images/name.png",
      "message": "Jeong yonghoon"
    },
    {
      "id": 1,
      "imagePath": "assets/images/live.png",
      "message": "경기도 평택시"
    },
    {
      "id": 2,
      "imagePath": "assets/images/mail.png",
      "message": "jyh.dev@gmail.com"
    },
    {
      "id": 3,
      "imagePath": "assets/images/github.png",
      "message": "github.com/jyh4479"
    }
  ],

  "containerData2":[
    {
      "id": 4,
      "imagePath": "assets/images/phone.png",
      "message": "010-xxxx-xxxx"
    },
    {
      "id": 5,
      "imagePath": "assets/images/bag.png",
      "message": "KOLON-Benit"
    },
    {
      "id": 6,
      "imagePath": "assets/images/study.png",
      "message": "I hope to study full-stack"
    }
  ]
}